{
  "name": "pipe_connection",
  "components": {
    "com.locochoco.gameengine.Transform": {
      "position": {
        "x": 0,
        "y": 0
      }
    },
    "com.locochoco.game.RoomExitPipe": {},
    "com.locochoco.gameengine.SpriteRenderer": {
      "layer": "foreground",
      "file_name": "assets/enviroment/pipe/pipe.png"
    }
  },
  "children": [
    {
      "name": "flash",
      "components": {
        "com.locochoco.gameengine.Transform": {
          "position": {
            "x": 0,
            "y": 0
          }
        },
        "com.locochoco.gameengine.BoxRenderer": {
          "layer": "foreground_back_detail",
          "width": 5,
          "height": 5,
          "center": null
        }
      }
    }
  ]
}
